translate/__init__.py
translate/__main__.py
translate/constants.py
translate/exceptions.py
translate/main.py
translate/translate.py
translate/version.py
translate/providers/__init__.py
translate/providers/base.py
translate/providers/deepl.py
translate/providers/libre.py
translate/providers/microsoft.py
translate/providers/mymemory_translated.py
translate-3.6.0.dist-info/LICENSE
translate-3.6.0.dist-info/METADATA
translate-3.6.0.dist-info/WHEEL
translate-3.6.0.dist-info/entry_points.txt
translate-3.6.0.dist-info/top_level.txt
translate-3.6.0.dist-info/RECORD
