Metadata-Version: 2.1
Name: translate
Version: 3.6.0
Summary: This is a simple, yet powerful command line translator with google translate behind it. You can also use it as a Python module in your code.
Home-page: https://github.com/terryyin/google-translate-python
Author: Terry Yin
Author-email: terry.yinze@gmail.com
License: MIT
Keywords: translate translation command line
Platform: UNKNOWN
Classifier: Development Status :: 5 - Production/Stable
Classifier: Intended Audience :: Education
Classifier: Intended Audience :: End Users/Desktop
Classifier: Intended Audience :: Developers
Classifier: License :: OSI Approved :: MIT License
Classifier: Operating System :: OS Independent
Classifier: Programming Language :: Python :: 2.6
Classifier: Programming Language :: Python :: 2.7
Classifier: Programming Language :: Python :: 3.5
Classifier: Programming Language :: Python
Classifier: Topic :: Education
Requires-Dist: click
Requires-Dist: lxml
Requires-Dist: requests
Requires-Dist: libretranslatepy (==2.1.1)
